{"is_source_file": false, "format": "", "description": "", "external_files": [], "external_methods": [], "published": [], "classes": [], "methods": [], "calls": [], "search-terms": [], "state": 2, "file_id": 15, "knowledge_revision": 26, "git_revision": "cd2d53a77cefbcf603ddce3f6ca39ebaf18df736", "hash": "a88a471f435da6e3fe5e31affcd559af", "format-version": 4, "code-base-name": "angular_19_frontend", "filename": "angular_19_frontend/tsconfig.app.json", "revision_history": [{"26": "cd2d53a77cefbcf603ddce3f6ca39ebaf18df736"}]}